strcolored/__init__.py
strcolored/test.py
strcolored-2.8.dist-info/METADATA
strcolored-2.8.dist-info/WHEEL
strcolored-2.8.dist-info/top_level.txt
strcolored-2.8.dist-info/RECORD
