Metadata-Version: 2.1
Name: strcolored
Version: 2.8
Summary: python library for colored strings
Author-email: media.hr@execs.com
License: Eclipse Public License 2.0
